MANIFEST.in
README.rst
setup.cfg
setup.py
version.py
src/cgcloud/__init__.py
src/cgcloud/jenkins/__init__.py
src/cgcloud/jenkins/cgcloud_jenkins_slave.py
src/cgcloud/jenkins/commands.py
src/cgcloud/jenkins/docker_jenkins_slave.py
src/cgcloud/jenkins/generic_jenkins_slaves.py
src/cgcloud/jenkins/jenkins_master.py
src/cgcloud/jenkins/jenkins_slave.py
src/cgcloud/jenkins/rpmbuild_jenkins_slaves.py
src/cgcloud/jenkins/s3am_jenkins_slave.py
src/cgcloud/jenkins/toil_jenkins_slave.py
src/cgcloud/jenkins/test/__init__.py
src/cgcloud/jenkins/test/conftest.py
src/cgcloud/jenkins/test/create_all_slaves.py
src/cgcloud_jenkins.egg-info/PKG-INFO
src/cgcloud_jenkins.egg-info/SOURCES.txt
src/cgcloud_jenkins.egg-info/dependency_links.txt
src/cgcloud_jenkins.egg-info/namespace_packages.txt
src/cgcloud_jenkins.egg-info/requires.txt
src/cgcloud_jenkins.egg-info/top_level.txt