Metadata-Version: 1.0
Name: cgcloud-jenkins
Version: 1.6.0a1.dev397
Summary: Setup and manage a Jenkins continuous integration cluster in EC2
Home-page: https://github.com/BD2KGenomics/cgcloud
Author: Hannes Schmidt
Author-email: hannes@ucsc.edu
License: UNKNOWN
Platform: UNKNOWN
